gitblobts/__init__.py
gitblobts/config.py
gitblobts/exc.py
gitblobts/logging.conf
gitblobts/store.py
gitblobts/util/__init__.py
gitblobts/util/int_base_encoder.py
gitblobts/util/int_merger.py
gitblobts-0.0.7.dist-info/LICENSE
gitblobts-0.0.7.dist-info/METADATA
gitblobts-0.0.7.dist-info/WHEEL
gitblobts-0.0.7.dist-info/top_level.txt
gitblobts-0.0.7.dist-info/RECORD
