Metadata-Version: 2.1
Name: gitblobts
Version: 0.0.7
Summary: git-backed time-indexed blob storage
Home-page: https://github.com/impredicative/gitblobts/
Author: Ouroboros Chrysopoeia
Author-email: impredicative@users.nomail.github.com
License: UNKNOWN
Keywords: git bytes mirroring storage time
Platform: UNKNOWN
Classifier: Programming Language :: Python :: 3.7
Classifier: License :: OSI Approved :: GNU Affero General Public License v3
Classifier: Topic :: Communications :: File Sharing
Classifier: Topic :: Software Development :: Version Control :: Git
Classifier: Topic :: System :: Archiving
Classifier: Topic :: System :: Archiving :: Mirroring
Requires-Python: >=3.7
Requires-Dist: cryptography (>=2.4.2)
Requires-Dist: dateparser (>=0.7.0)
Requires-Dist: gitpython (>=2.1.11)
